Workbook

Sheet Read Me & Assumptions
A1: FLOW | Phase 4 Financial Decision Model
A2: Seven-tab workbook • Synthetic data • INR • Historical period: Oct 2025–Sep 2026
A4: Model control | B4: Value | C4: Status / source
A5: Project | B5: Customer Onboarding Throughput Transformation | C5: Northstar Cloud Services is fictional
A6: Data classification | B6: Synthetic | C6: No real customer or employer data
A7: Historical period | B7: Oct 2025 – Sep 2026 | C7: 12 months
A8: Management completion target | B8: 240 | C8: Decision target; not historical result
A9: SLA | B9: 35 | C9: Calendar days; defined in KPI_definitions.md
A10: Capacity-hours rule | B10: monthly_capacity_hours is already FTE-adjusted | C10: Do not multiply by FTE_fraction again
A11: Historical average completions / month | B11: 180.6 | C11: Calculated from 12 monthly SQL rows
A12: Historical average receipts / month | B12: 209 | C12: Calculated from 12 monthly SQL rows
A13: Mean calendar cycle time (days) | B13: 40.8 | C13: Phase 3 overall summary
A14: Median calendar cycle time (days) | B14: 35.1 | C14: Phase 3 overall summary
A15: P90 calendar cycle time (days) | B15: 70 | C15: Phase 3 overall summary
A16: SLA attainment | B16: 0.492 | C16: Phase 3 overall summary
A17: Application rework rate | B17: 0.199 | C17: 530 / 2,665 eligible applications
A18: Qualifying rework events (recomputed) | B18: 571 | C18: Raw rework_events joined to applications; positive minutes; non-Invalid status
A19: Qualifying rework minutes (recomputed) | B19: 29814 | C19: Same event rule as above; see Cost Build
A20: Owner monthly capacity hours (sum) | B20: 3631 | C20: 31 owner records; capacity already FTE-adjusted
A21: Weighted owner hourly cost | B21: 682.65767 | C21: Weighted by monthly capacity hours; proxy for cost estimation
A22: Leading bottleneck | B22: Finance Approval | C22: Composite bottleneck evidence ranking
A25: EDITABLE SCENARIO ASSUMPTIONS — provisional, not observed results
A26: Assumption | B26: Conservative | C26: Base | D26: Optimistic | E26: Rationale / caveat
A27: Monthly demand growth | B27: 0.03 | C27: 0.02 | D27: 0.01 | E27: Planning assumption; validate against business outlook
A28: Redesign throughput uplift | B28: 0.03 | C28: 0.1 | D28: 0.18 | E28: Proxy uplift to historical completions, not measured effect
A29: Redesign rework reduction | B29: 0.05 | C29: 0.15 | D29: 0.25 | E29: Applied to qualifying rework labour cost only
A30: Added FTE count | B30: 3 | C30: 2 | D30: 1 | E30: Scenario assumption; does not establish actual staffing need
A31: Monthly cost per added FTE (INR) | B31: 120000 | C31: 100000 | D31: 85000 | E31: Illustrative loaded monthly cost; replace with evidence
A32: One-time redesign implementation cost (INR) | B32: 500000 | C32: 350000 | D32: 250000 | E32: Illustrative estimate
A33: One-time hiring/setup cost per FTE (INR) | B33: 50000 | C33: 40000 | D33: 30000 | E33: Illustrative estimate per added FTE
A34: Added monthly capacity hours per FTE | B34: 95 | C34: 95 | D34: 95 | E34: Illustrative standard capacity assumption
A35: Ramp-up months | B35: 4 | C35: 3 | D35: 2 | E35: Time before full modelled benefits
A36: Other recurring redesign cost / month (INR) | B36: 30000 | C36: 20000 | D36: 15000 | E36: Illustrative support/tool/process cost
A37: Additional throughput per added FTE / month | B37: 8 | C37: 12 | D37: 16 | E37: Explicit productivity proxy; validate with capacity/workload evidence
A38: Rework event active labour cost rate (INR/hour) | B38: 682.65767 | C38: 682.65767 | D38: 682.65767 | E38: Owner hourly rate proxy; rework minutes are estimates
A40: MODEL LIMITATION: Actual active labour hours are not directly measured by task timestamps. Capacity and intervention results are planning estimates. Released capacity is not cash savings. Do not claim modelled benefits as realised.

Sheet Monthly Demand
A1: Monthly Demand & Backlog
A2: Historical monthly flow imported from Phase 3 SQL export; forecast is separate and assumption-driven
A4: Month | B4: Opening backlog | C4: Received | D4: Completed | E4: Cancelled | F4: Calculated closing backlog | G4: SQL closing backlog | H4: Variance | I4: Check
A5: 2025-10 | B5: 203 | C5: 158 | D5: 136 | E5: 16 | F5: =B5+C5-D5-E5 -> 209 | G5: 209 | H5: =F5-G5 -> 0 | I5: =IF(H5=0,"PASS","FAIL") -> PASS
A6: 2025-11 | B6: 209 | C6: 183 | D6: 139 | E6: 11 | F6: =B6+C6-D6-E6 -> 242 | G6: 242 | H6: =F6-G6 -> 0 | I6: =IF(AND(H6=0,OR(ROW()=5,B6=F5)),"PASS","FAIL") -> PASS
A7: 2025-12 | B7: 242 | C7: 179 | D7: 174 | E7: 18 | F7: =B7+C7-D7-E7 -> 229 | G7: 229 | H7: =F7-G7 -> 0 | I7: =IF(AND(H7=0,OR(ROW()=5,B7=F6)),"PASS","FAIL") -> PASS
A8: 2026-01 | B8: 229 | C8: 159 | D8: 152 | E8: 13 | F8: =B8+C8-D8-E8 -> 223 | G8: 223 | H8: =F8-G8 -> 0 | I8: =IF(AND(H8=0,OR(ROW()=5,B8=F7)),"PASS","FAIL") -> PASS
A9: 2026-02 | B9: 223 | C9: 177 | D9: 144 | E9: 11 | F9: =B9+C9-D9-E9 -> 245 | G9: 245 | H9: =F9-G9 -> 0 | I9: =IF(AND(H9=0,OR(ROW()=5,B9=F8)),"PASS","FAIL") -> PASS
A10: 2026-03 | B10: 245 | C10: 258 | D10: 183 | E10: 17 | F10: =B10+C10-D10-E10 -> 303 | G10: 303 | H10: =F10-G10 -> 0 | I10: =IF(AND(H10=0,OR(ROW()=5,B10=F9)),"PASS","FAIL") -> PASS
A11: 2026-04 | B11: 303 | C11: 198 | D11: 205 | E11: 16 | F11: =B11+C11-D11-E11 -> 280 | G11: 280 | H11: =F11-G11 -> 0 | I11: =IF(AND(H11=0,OR(ROW()=5,B11=F10)),"PASS","FAIL") -> PASS
A12: 2026-05 | B12: 280 | C12: 224 | D12: 183 | E12: 20 | F12: =B12+C12-D12-E12 -> 301 | G12: 301 | H12: =F12-G12 -> 0 | I12: =IF(AND(H12=0,OR(ROW()=5,B12=F11)),"PASS","FAIL") -> PASS
A13: 2026-06 | B13: 301 | C13: 222 | D13: 204 | E13: 15 | F13: =B13+C13-D13-E13 -> 304 | G13: 304 | H13: =F13-G13 -> 0 | I13: =IF(AND(H13=0,OR(ROW()=5,B13=F12)),"PASS","FAIL") -> PASS
A14: 2026-07 | B14: 304 | C14: 246 | D14: 226 | E14: 20 | F14: =B14+C14-D14-E14 -> 304 | G14: 304 | H14: =F14-G14 -> 0 | I14: =IF(AND(H14=0,OR(ROW()=5,B14=F13)),"PASS","FAIL") -> PASS
A15: 2026-08 | B15: 304 | C15: 240 | D15: 223 | E15: 12 | F15: =B15+C15-D15-E15 -> 309 | G15: 309 | H15: =F15-G15 -> 0 | I15: =IF(AND(H15=0,OR(ROW()=5,B15=F14)),"PASS","FAIL") -> PASS
A16: 2026-09 | B16: 309 | C16: 264 | D16: 198 | E16: 15 | F16: =B16+C16-D16-E16 -> 360 | G16: 360 | H16: =F16-G16 -> 0 | I16: =IF(AND(H16=0,OR(ROW()=5,B16=F15)),"PASS","FAIL") -> PASS
A19: 12-MONTH FORECAST — base demand case; forecast is illustrative and not historical
A20: Month | B20: Opening backlog | C20: Forecast receipts | D20: Modelled completions | E20: Assumed cancellations | F20: Forecast closing backlog | G20: Target completions | H20: Gap vs target | I20: Forecast check
A21: 2026-10 | B21: =F16 -> 360 | C21: =ROUND(AVERAGE($C$5:$C$16)*(1+'Read Me & Assumptions'!$C$27)^1,0) -> 213 | D21: =ROUND(AVERAGE($D$5:$D$16),0) -> 181 | E21: =ROUND(AVERAGE($E$5:$E$16),0) -> 15 | F21: =MAX(0,B21+C21-D21-E21) -> 377 | G21: ='Read Me & Assumptions'!$B$8 -> 240 | H21: =MAX(0,G21-D21) -> 59 | I21: =IF(F21>=0,"PASS","REVIEW") -> PASS
A22: 2026-11 | B22: =F21 -> 377 | C22: =ROUND(AVERAGE($C$5:$C$16)*(1+'Read Me & Assumptions'!$C$27)^2,0) -> 217 | D22: =ROUND(AVERAGE($D$5:$D$16),0) -> 181 | E22: =ROUND(AVERAGE($E$5:$E$16),0) -> 15 | F22: =MAX(0,B22+C22-D22-E22) -> 398 | G22: ='Read Me & Assumptions'!$B$8 -> 240 | H22: =MAX(0,G22-D22) -> 59 | I22: =IF(F22>=0,"PASS","REVIEW") -> PASS
A23: 2026-12 | B23: =F22 -> 398 | C23: =ROUND(AVERAGE($C$5:$C$16)*(1+'Read Me & Assumptions'!$C$27)^3,0) -> 222 | D23: =ROUND(AVERAGE($D$5:$D$16),0) -> 181 | E23: =ROUND(AVERAGE($E$5:$E$16),0) -> 15 | F23: =MAX(0,B23+C23-D23-E23) -> 424 | G23: ='Read Me & Assumptions'!$B$8 -> 240 | H23: =MAX(0,G23-D23) -> 59 | I23: =IF(F23>=0,"PASS","REVIEW") -> PASS
A24: 2027-01 | B24: =F23 -> 424 | C24: =ROUND(AVERAGE($C$5:$C$16)*(1+'Read Me & Assumptions'!$C$27)^4,0) -> 226 | D24: =ROUND(AVERAGE($D$5:$D$16),0) -> 181 | E24: =ROUND(AVERAGE($E$5:$E$16),0) -> 15 | F24: =MAX(0,B24+C24-D24-E24) -> 454 | G24: ='Read Me & Assumptions'!$B$8 -> 240 | H24: =MAX(0,G24-D24) -> 59 | I24: =IF(F24>=0,"PASS","REVIEW") -> PASS
A25: 2027-02 | B25: =F24 -> 454 | C25: =ROUND(AVERAGE($C$5:$C$16)*(1+'Read Me & Assumptions'!$C$27)^5,0) -> 231 | D25: =ROUND(AVERAGE($D$5:$D$16),0) -> 181 | E25: =ROUND(AVERAGE($E$5:$E$16),0) -> 15 | F25: =MAX(0,B25+C25-D25-E25) -> 489 | G25: ='Read Me & Assumptions'!$B$8 -> 240 | H25: =MAX(0,G25-D25) -> 59 | I25: =IF(F25>=0,"PASS","REVIEW") -> PASS
A26: 2027-03 | B26: =F25 -> 489 | C26: =ROUND(AVERAGE($C$5:$C$16)*(1+'Read Me & Assumptions'!$C$27)^6,0) -> 235 | D26: =ROUND(AVERAGE($D$5:$D$16),0) -> 181 | E26: =ROUND(AVERAGE($E$5:$E$16),0) -> 15 | F26: =MAX(0,B26+C26-D26-E26) -> 528 | G26: ='Read Me & Assumptions'!$B$8 -> 240 | H26: =MAX(0,G26-D26) -> 59 | I26: =IF(F26>=0,"PASS","REVIEW") -> PASS
A27: 2027-04 | B27: =F26 -> 528 | C27: =ROUND(AVERAGE($C$5:$C$16)*(1+'Read Me & Assumptions'!$C$27)^7,0) -> 240 | D27: =ROUND(AVERAGE($D$5:$D$16),0) -> 181 | E27: =ROUND(AVERAGE($E$5:$E$16),0) -> 15 | F27: =MAX(0,B27+C27-D27-E27) -> 572 | G27: ='Read Me & Assumptions'!$B$8 -> 240 | H27: =MAX(0,G27-D27) -> 59 | I27: =IF(F27>=0,"PASS","REVIEW") -> PASS
A28: 2027-05 | B28: =F27 -> 572 | C28: =ROUND(AVERAGE($C$5:$C$16)*(1+'Read Me & Assumptions'!$C$27)^8,0) -> 245 | D28: =ROUND(AVERAGE($D$5:$D$16),0) -> 181 | E28: =ROUND(AVERAGE($E$5:$E$16),0) -> 15 | F28: =MAX(0,B28+C28-D28-E28) -> 621 | G28: ='Read Me & Assumptions'!$B$8 -> 240 | H28: =MAX(0,G28-D28) -> 59 | I28: =IF(F28>=0,"PASS","REVIEW") -> PASS
A29: 2027-06 | B29: =F28 -> 621 | C29: =ROUND(AVERAGE($C$5:$C$16)*(1+'Read Me & Assumptions'!$C$27)^9,0) -> 250 | D29: =ROUND(AVERAGE($D$5:$D$16),0) -> 181 | E29: =ROUND(AVERAGE($E$5:$E$16),0) -> 15 | F29: =MAX(0,B29+C29-D29-E29) -> 675 | G29: ='Read Me & Assumptions'!$B$8 -> 240 | H29: =MAX(0,G29-D29) -> 59 | I29: =IF(F29>=0,"PASS","REVIEW") -> PASS
A30: 2027-07 | B30: =F29 -> 675 | C30: =ROUND(AVERAGE($C$5:$C$16)*(1+'Read Me & Assumptions'!$C$27)^10,0) -> 255 | D30: =ROUND(AVERAGE($D$5:$D$16),0) -> 181 | E30: =ROUND(AVERAGE($E$5:$E$16),0) -> 15 | F30: =MAX(0,B30+C30-D30-E30) -> 734 | G30: ='Read Me & Assumptions'!$B$8 -> 240 | H30: =MAX(0,G30-D30) -> 59 | I30: =IF(F30>=0,"PASS","REVIEW") -> PASS
A31: 2027-08 | B31: =F30 -> 734 | C31: =ROUND(AVERAGE($C$5:$C$16)*(1+'Read Me & Assumptions'!$C$27)^11,0) -> 260 | D31: =ROUND(AVERAGE($D$5:$D$16),0) -> 181 | E31: =ROUND(AVERAGE($E$5:$E$16),0) -> 15 | F31: =MAX(0,B31+C31-D31-E31) -> 798 | G31: ='Read Me & Assumptions'!$B$8 -> 240 | H31: =MAX(0,G31-D31) -> 59 | I31: =IF(F31>=0,"PASS","REVIEW") -> PASS
A32: 2027-09 | B32: =F31 -> 798 | C32: =ROUND(AVERAGE($C$5:$C$16)*(1+'Read Me & Assumptions'!$C$27)^12,0) -> 265 | D32: =ROUND(AVERAGE($D$5:$D$16),0) -> 181 | E32: =ROUND(AVERAGE($E$5:$E$16),0) -> 15 | F32: =MAX(0,B32+C32-D32-E32) -> 867 | G32: ='Read Me & Assumptions'!$B$8 -> 240 | H32: =MAX(0,G32-D32) -> 59 | I32: =IF(F32>=0,"PASS","REVIEW") -> PASS

Sheet Current-State Capacity
A1: Current-State Capacity
A2: Team/month capacity and complexity indicators from Phase 3; complexity points are not active labour hours
A4: Month | B4: Team | C4: Stage episodes entered | D4: Complexity points | E4: Capacity hours | F4: Points / 100 capacity hours | H4: Interpretation
A5: 2025-10 | B5: Sales | C5: 167 | D5: 308 | E5: 510 | F5: =IFERROR(D5/E5*100,0) -> 60.392157 | H5: Workload intensity proxy; not a direct utilisation or active-hours measure.
A6: 2025-10 | B6: RevOps | C6: 175 | D6: 330 | E6: 336 | F6: =IFERROR(D6/E6*100,0) -> 98.214286 | H6: Workload intensity proxy; not a direct utilisation or active-hours measure.
A7: 2025-10 | B7: Legal | C7: 159 | D7: 299 | E7: 375 | F7: =IFERROR(D7/E7*100,0) -> 79.733333 | H7: Workload intensity proxy; not a direct utilisation or active-hours measure.
A8: 2025-10 | B8: Implementation | C8: 312 | D8: 575 | E8: 1548 | F8: =IFERROR(D8/E8*100,0) -> 37.144703 | H8: Workload intensity proxy; not a direct utilisation or active-hours measure.
A9: 2025-10 | B9: Finance | C9: 157 | D9: 292 | E9: 247 | F9: =IFERROR(D9/E9*100,0) -> 118.21862 | H9: Workload intensity proxy; not a direct utilisation or active-hours measure.
A10: 2025-10 | B10: Customer Success | C10: 142 | D10: 255 | E10: 360 | F10: =IFERROR(D10/E10*100,0) -> 70.833333 | H10: Workload intensity proxy; not a direct utilisation or active-hours measure.
A11: 2025-11 | B11: Sales | C11: 201 | D11: 392 | E11: 510 | F11: =IFERROR(D11/E11*100,0) -> 76.862745 | H11: Workload intensity proxy; not a direct utilisation or active-hours measure.
A12: 2025-11 | B12: RevOps | C12: 212 | D12: 409 | E12: 336 | F12: =IFERROR(D12/E12*100,0) -> 121.72619 | H12: Workload intensity proxy; not a direct utilisation or active-hours measure.
A13: 2025-11 | B13: Legal | C13: 192 | D13: 369 | E13: 375 | F13: =IFERROR(D13/E13*100,0) -> 98.4 | H13: Workload intensity proxy; not a direct utilisation or active-hours measure.
A14: 2025-11 | B14: Implementation | C14: 295 | D14: 539 | E14: 1548 | F14: =IFERROR(D14/E14*100,0) -> 34.819121 | H14: Workload intensity proxy; not a direct utilisation or active-hours measure.
A15: 2025-11 | B15: Finance | C15: 158 | D15: 287 | E15: 247 | F15: =IFERROR(D15/E15*100,0) -> 116.19433 | H15: Workload intensity proxy; not a direct utilisation or active-hours measure.
A16: 2025-11 | B16: Customer Success | C16: 138 | D16: 249 | E16: 360 | F16: =IFERROR(D16/E16*100,0) -> 69.166667 | H16: Workload intensity proxy; not a direct utilisation or active-hours measure.
... A76: 2026-09 | B76: Customer Success | C76: 201 | D76: 370 | E76: 360 | F76: =IFERROR(D76/E76*100,0) -> 102.77778 | H76: Workload intensity proxy; not a direct utilisation or active-hours measure.
A79: Owner-level detail (raw owner table + Phase 3 workload measures)
A80: Owner ID | B80: Team | C80: FTE fraction | D80: Monthly capacity hours (already FTE-adjusted) | E80: Cost per hour (INR) | H80: Complexity points / capacity hour
A81: S01 | B81: Sales | C81: 1 | D81: 75 | E81: 710 | H81: 0.571
A82: S02 | B82: Sales | C82: 1 | D82: 75 | E82: 770 | H82: 0.535
A83: S03 | B83: Sales | C83: 1 | D83: 75 | E83: 790 | H83: 0.634
A84: S04 | B84: Sales | C84: 1 | D84: 75 | E84: 700 | H84: 0.631
A85: S05 | B85: Sales | C85: 1 | D85: 75 | E85: 660 | H85: 0.821
A86: S06 | B86: Sales | C86: 0.8 | D86: 60 | E86: 680 | H86: 0.913
A87: S07 | B87: Sales | C87: 1 | D87: 75 | E87: 800 | H87: 0.9
A88: S08 | B88: Sales | C88: 1 | D88: 75 | E88: 760 | H88: 1.114
A89: R01 | B89: RevOps | C89: 0.8 | D89: 96 | E89: 570 | H89: 1.275
A90: R02 | B90: RevOps | C90: 1 | D90: 120 | E90: 620 | H90: 1.251
A91: R03 | B91: RevOps | C91: 1 | D91: 120 | E91: 540 | H91: 1.374
A92: L01 | B92: Legal | C92: 1 | D92: 150 | E92: 1030 | H92: 0.962
... A111: C04 | B111: Customer Success | C111: 1 | D111: 90 | E111: 500 | H111: 1.121
A114: Interpretation
A115: The provided team dataset measures complexity points per capacity hour. It does not establish active labour hours or a direct throughput-per-hour relationship. Scenario throughput uplifts are therefore explicit planning assumptions, not a causal finding.

Sheet Cost Build
A1: Cost Build
A2: Source-supported rework estimate and transparent placeholders; do not interpret elapsed time as active labour
A4: Cost component | B4: Value | C4: Unit | D4: Source / formula | E4: Evidence status
A5: Completed applications | B5: 2167 | C5: applications | D5: Phase 3 scalar validation | E5: Observed synthetic-data count
A6: Qualifying rework events | B6: 571 | C6: events | D6: Raw events linked to application; positive minutes; status not Invalid | E6: Recomputed from raw data
A7: Qualifying estimated rework minutes | B7: 29814 | C7: minutes | D7: Same qualifying-event rule | E7: Estimated effort input
A8: Qualifying estimated rework hours | B8: =B7/60 -> 496.9 | C8: hours | D8: Minutes / 60 | E8: Derived estimate
A9: Capacity-weighted owner cost rate | B9: 682.65767 | C9: INR/hour | D9: Owner monthly capacity-weighted cost per hour | E9: Proxy
A10: Estimated rework labour cost | B10: =B8*B9 -> 339212.6 | C10: INR | D10: Estimated rework hours × weighted cost rate | E10: Modelled estimate
A11: Estimated rework cost per completed application | B11: =B10/B5 -> 156.53558 | C11: INR/application | D11: Estimated rework labour cost / completed applications | E11: Modelled estimate
A12: Other direct cost per completion | B12: 8000 | C12: INR/application | D12: Provisional placeholder from initial planning hypothesis; not validated as actual | E12: Assumption — replace
A13: Illustrative total cost per completion | B13: =B11+B12 -> 8156.5356 | C13: INR/application | D13: Rework estimate + provisional other cost; incomplete cost build | E13: Illustrative only
A14: Illustrative monthly cost at target | B14: =B13*'Read Me & Assumptions'!$B$8 -> 1957568.5 | C14: INR/month | D14: Illustrative unit cost × 240 target | E14: Illustrative only
A15: Annual qualifying rework labour cost | B15: =B10 -> 339212.6 | C15: INR/year | D15: Estimated qualifying rework labour cost across the 12-month historical period; not annualised again | E15: Historical-period estimate; not a forward annual forecast
A19: Cost interpretation and limitations
A20: • Task elapsed time is not a direct measure of hands-on labour; no task-duration cost is claimed as measured.
A21: • Rework estimated_minutes is itself an estimate. Cost uses a capacity-weighted owner hourly rate as a proxy, not a verified owner-to-event rate.
A22: • ₹8,000 per completion is a provisional planning hypothesis and must not be described as a validated historical cost.
A23: • Released capacity is not cash savings. Cashable savings require a defensible reduction in actual cash expenditure.
A24: • Do not add rework cost reduction, capacity release and incremental throughput as independent financial benefits without proving no overlap.

Sheet Intervention Scenarios
A1: Intervention Scenarios
A2: A–D comparison across conservative/base/optimistic cases; capacity effect is an explicit throughput proxy
A4: Option | B4: Scenario | C4: Demand / month | D4: Baseline throughput proxy | E4: Redesign uplift | F4: Added FTE | G4: Added throughput / FTE | H4: Modelled throughput | I4: Gap to demand | J4: One-time redesign cost | K4: One-time hiring cost | L4: Annual recurring cost | M4: First-year modelled cost | N4: Gap to 240 target | O4: Estimated rework cost reduction proxy (INR/year) | P4: Ramp-up-adjusted recurring cost (INR) | Q4: Net modelled first-year impact (INR; proxy only) | R4: Recurring annual cost after ramp-up (INR) | S4: Uncapped modelled capacity
A5: A — No change | B5: Conservative | C5: =AVERAGE('Monthly Demand'!$C$5:$C$16)*(1+'Read Me & Assumptions'!$B$27) -> 215.27 | D5: =AVERAGE('Monthly Demand'!$D$5:$D$16) -> 180.58333 | E5: 0 | F5: 0 | G5: 0 | H5: =MIN(C5,D5*(1+E5)+F5*G5) -> 180.58333 | I5: =MAX(0,C5-H5) -> 34.686667 | J5: 0 | K5: 0 | L5: =IF(OR(A5="B — Process redesign",A5="D — Redesign + targeted staffing"),'Read Me & Assumptions'!$B$36*12,0)+IF(F5>0,F5*'Read Me & Assumptions'!$B$31*12,0) -> 0 | M5: =J5+K5+L5 -> 0 | N5: =MAX(0,'Read Me & Assumptions'!$B$8-S5) -> 59.416667 | O5: =IF(OR(A5="B — Process redesign",A5="D — Redesign + targeted staffing"),'Cost Build'!$B$8*'Read Me & Assumptions'!$B$38*'Read Me & Assumptions'!$B$29*(12-'Read Me & Assumptions'!$B$35)/12,0) -> 0 | P5: =IF(OR(A5="B — Process redesign",A5="D — Redesign + targeted staffing"),'Read Me & Assumptions'!$B$36*(12-'Read Me & Assumptions'!$B$35),0)+IF(F5>0,F5*'Read Me & Assumptions'!$B$31*(12-'Read Me & Assumptions'!$B$35),0) -> 0 | Q5: =O5-M5 -> 0 | R5: =IF(OR(A5="B — Process redesign",A5="D — Redesign + targeted staffing"),'Read Me & Assumptions'!$B$36*12,0)+IF(F5>0,F5*'Read Me & Assumptions'!$B$31*12,0) -> 0 | S5: =D5*(1+E5)+F5*G5 -> 180.58333
A6: A — No change | B6: Base | C6: =AVERAGE('Monthly Demand'!$C$5:$C$16)*(1+'Read Me & Assumptions'!$C$27) -> 213.18 | D6: =AVERAGE('Monthly Demand'!$D$5:$D$16) -> 180.58333 | E6: 0 | F6: 0 | G6: 0 | H6: =MIN(C6,D6*(1+E6)+F6*G6) -> 180.58333 | I6: =MAX(0,C6-H6) -> 32.596667 | J6: 0 | K6: 0 | L6: =IF(OR(A6="B — Process redesign",A6="D — Redesign + targeted staffing"),'Read Me & Assumptions'!$C$36*12,0)+IF(F6>0,F6*'Read Me & Assumptions'!$C$31*12,0) -> 0 | M6: =J6+K6+L6 -> 0 | N6: =MAX(0,'Read Me & Assumptions'!$B$8-S6) -> 59.416667 | O6: =IF(OR(A6="B — Process redesign",A6="D — Redesign + targeted staffing"),'Cost Build'!$B$8*'Read Me & Assumptions'!$C$38*'Read Me & Assumptions'!$C$29*(12-'Read Me & Assumptions'!$C$35)/12,0) -> 0 | P6: =IF(OR(A6="B — Process redesign",A6="D — Redesign + targeted staffing"),'Read Me & Assumptions'!$C$36*(12-'Read Me & Assumptions'!$C$35),0)+IF(F6>0,F6*'Read Me & Assumptions'!$C$31*(12-'Read Me & Assumptions'!$C$35),0) -> 0 | Q6: =O6-M6 -> 0 | R6: =IF(OR(A6="B — Process redesign",A6="D — Redesign + targeted staffing"),'Read Me & Assumptions'!$C$36*12,0)+IF(F6>0,F6*'Read Me & Assumptions'!$C$31*12,0) -> 0 | S6: =D6*(1+E6)+F6*G6 -> 180.58333
A7: A — No change | B7: Optimistic | C7: =AVERAGE('Monthly Demand'!$C$5:$C$16)*(1+'Read Me & Assumptions'!$D$27) -> 211.09 | D7: =AVERAGE('Monthly Demand'!$D$5:$D$16) -> 180.58333 | E7: 0 | F7: 0 | G7: 0 | H7: =MIN(C7,D7*(1+E7)+F7*G7) -> 180.58333 | I7: =MAX(0,C7-H7) -> 30.506667 | J7: 0 | K7: 0 | L7: =IF(OR(A7="B — Process redesign",A7="D — Redesign + targeted staffing"),'Read Me & Assumptions'!$D$36*12,0)+IF(F7>0,F7*'Read Me & Assumptions'!$D$31*12,0) -> 0 | M7: =J7+K7+L7 -> 0 | N7: =MAX(0,'Read Me & Assumptions'!$B$8-S7) -> 59.416667 | O7: =IF(OR(A7="B — Process redesign",A7="D — Redesign + targeted staffing"),'Cost Build'!$B$8*'Read Me & Assumptions'!$D$38*'Read Me & Assumptions'!$D$29*(12-'Read Me & Assumptions'!$D$35)/12,0) -> 0 | P7: =IF(OR(A7="B — Process redesign",A7="D — Redesign + targeted staffing"),'Read Me & Assumptions'!$D$36*(12-'Read Me & Assumptions'!$D$35),0)+IF(F7>0,F7*'Read Me & Assumptions'!$D$31*(12-'Read Me & Assumptions'!$D$35),0) -> 0 | Q7: =O7-M7 -> 0 | R7: =IF(OR(A7="B — Process redesign",A7="D — Redesign + targeted staffing"),'Read Me & Assumptions'!$D$36*12,0)+IF(F7>0,F7*'Read Me & Assumptions'!$D$31*12,0) -> 0 | S7: =D7*(1+E7)+F7*G7 -> 180.58333
A8: B — Process redesign | B8: Conservative | C8: =AVERAGE('Monthly Demand'!$C$5:$C$16)*(1+'Read Me & Assumptions'!$B$27) -> 215.27 | D8: =AVERAGE('Monthly Demand'!$D$5:$D$16) -> 180.58333 | E8: ='Read Me & Assumptions'!$B$28 -> 0.03 | F8: 0 | G8: 0 | H8: =MIN(C8,D8*(1+E8)+F8*G8) -> 186.00083 | I8: =MAX(0,C8-H8) -> 29.269167 | J8: ='Read Me & Assumptions'!$B$32 -> 500000 | K8: 0 | L8: =IF(OR(A8="B — Process redesign",A8="D — Redesign + targeted staffing"),'Read Me & Assumptions'!$B$36*12,0)+IF(F8>0,F8*'Read Me & Assumptions'!$B$31*12,0) -> 360000 | M8: =J8+K8+L8 -> 860000 | N8: =MAX(0,'Read Me & Assumptions'!$B$8-S8) -> 53.999167 | O8: =IF(OR(A8="B — Process redesign",A8="D — Redesign + targeted staffing"),'Cost Build'!$B$8*'Read Me & Assumptions'!$B$38*'Read Me & Assumptions'!$B$29*(12-'Read Me & Assumptions'!$B$35)/12,0) -> 11307.087 | P8: =IF(OR(A8="B — Process redesign",A8="D — Redesign + targeted staffing"),'Read Me & Assumptions'!$B$36*(12-'Read Me & Assumptions'!$B$35),0)+IF(F8>0,F8*'Read Me & Assumptions'!$B$31*(12-'Read Me & Assumptions'!$B$35),0) -> 240000 | Q8: =O8-M8 -> -848692.91 | R8: =IF(OR(A8="B — Process redesign",A8="D — Redesign + targeted staffing"),'Read Me & Assumptions'!$B$36*12,0)+IF(F8>0,F8*'Read Me & Assumptions'!$B$31*12,0) -> 360000 | S8: =D8*(1+E8)+F8*G8 -> 186.00083
A9: B — Process redesign | B9: Base | C9: =AVERAGE('Monthly Demand'!$C$5:$C$16)*(1+'Read Me & Assumptions'!$C$27) -> 213.18 | D9: =AVERAGE('Monthly Demand'!$D$5:$D$16) -> 180.58333 | E9: ='Read Me & Assumptions'!$C$28 -> 0.1 | F9: 0 | G9: 0 | H9: =MIN(C9,D9*(1+E9)+F9*G9) -> 198.64167 | I9: =MAX(0,C9-H9) -> 14.538333 | J9: ='Read Me & Assumptions'!$C$32 -> 350000 | K9: 0 | L9: =IF(OR(A9="B — Process redesign",A9="D — Redesign + targeted staffing"),'Read Me & Assumptions'!$C$36*12,0)+IF(F9>0,F9*'Read Me & Assumptions'!$C$31*12,0) -> 240000 | M9: =J9+K9+L9 -> 590000 | N9: =MAX(0,'Read Me & Assumptions'!$B$8-S9) -> 41.358333 | O9: =IF(OR(A9="B — Process redesign",A9="D — Redesign + targeted staffing"),'Cost Build'!$B$8*'Read Me & Assumptions'!$C$38*'Read Me & Assumptions'!$C$29*(12-'Read Me & Assumptions'!$C$35)/12,0) -> 38161.417 | P9: =IF(OR(A9="B — Process redesign",A9="D — Redesign + targeted staffing"),'Read Me & Assumptions'!$C$36*(12-'Read Me & Assumptions'!$C$35),0)+IF(F9>0,F9*'Read Me & Assumptions'!$C$31*(12-'Read Me & Assumptions'!$C$35),0) -> 180000 | Q9: =O9-M9 -> -551838.58 | R9: =IF(OR(A9="B — Process redesign",A9="D — Redesign + targeted staffing"),'Read Me & Assumptions'!$C$36*12,0)+IF(F9>0,F9*'Read Me & Assumptions'!$C$31*12,0) -> 240000 | S9: =D9*(1+E9)+F9*G9 -> 198.64167
A10: B — Process redesign | B10: Optimistic | C10: =AVERAGE('Monthly Demand'!$C$5:$C$16)*(1+'Read Me & Assumptions'!$D$27) -> 211.09 | D10: =AVERAGE('Monthly Demand'!$D$5:$D$16) -> 180.58333 | E10: ='Read Me & Assumptions'!$D$28 -> 0.18 | F10: 0 | G10: 0 | H10: =MIN(C10,D10*(1+E10)+F10*G10) -> 211.09 | I10: =MAX(0,C10-H10) -> 0 | J10: ='Read Me & Assumptions'!$D$32 -> 250000 | K10: 0 | L10: =IF(OR(A10="B — Process redesign",A10="D — Redesign + targeted staffing"),'Read Me & Assumptions'!$D$36*12,0)+IF(F10>0,F10*'Read Me & Assumptions'!$D$31*12,0) -> 180000 | M10: =J10+K10+L10 -> 430000 | N10: =MAX(0,'Read Me & Assumptions'!$B$8-S10) -> 26.911667 | O10: =IF(OR(A10="B — Process redesign",A10="D — Redesign + targeted staffing"),'Cost Build'!$B$8*'Read Me & Assumptions'!$D$38*'Read Me & Assumptions'!$D$29*(12-'Read Me & Assumptions'!$D$35)/12,0) -> 70669.291 | P10: =IF(OR(A10="B — Process redesign",A10="D — Redesign + targeted staffing"),'Read Me & Assumptions'!$D$36*(12-'Read Me & Assumptions'!$D$35),0)+IF(F10>0,F10*'Read Me & Assumptions'!$D$31*(12-'Read Me & Assumptions'!$D$35),0) -> 150000 | Q10: =O10-M10 -> -359330.71 | R10: =IF(OR(A10="B — Process redesign",A10="D — Redesign + targeted staffing"),'Read Me & Assumptions'!$D$36*12,0)+IF(F10>0,F10*'Read Me & Assumptions'!$D$31*12,0) -> 180000 | S10: =D10*(1+E10)+F10*G10 -> 213.08833
A11: C — Additional staffing | B11: Conservative | C11: =AVERAGE('Monthly Demand'!$C$5:$C$16)*(1+'Read Me & Assumptions'!$B$27) -> 215.27 | D11: =AVERAGE('Monthly Demand'!$D$5:$D$16) -> 180.58333 | E11: 0 | F11: ='Read Me & Assumptions'!$B$30 -> 3 | G11: ='Read Me & Assumptions'!$B$37*'Read Me & Assumptions'!$B$34/95 -> 8 | H11: =MIN(C11,D11*(1+E11)+F11*G11) -> 204.58333 | I11: =MAX(0,C11-H11) -> 10.686667 | J11: 0 | K11: =F11*'Read Me & Assumptions'!$B$33 -> 150000 | L11: =IF(OR(A11="B — Process redesign",A11="D — Redesign + targeted staffing"),'Read Me & Assumptions'!$B$36*12,0)+IF(F11>0,F11*'Read Me & Assumptions'!$B$31*12,0) -> 4320000 | M11: =J11+K11+L11 -> 4470000 | N11: =MAX(0,'Read Me & Assumptions'!$B$8-S11) -> 35.416667 | O11: =IF(OR(A11="B — Process redesign",A11="D — Redesign + targeted staffing"),'Cost Build'!$B$8*'Read Me & Assumptions'!$B$38*'Read Me & Assumptions'!$B$29*(12-'Read Me & Assumptions'!$B$35)/12,0) -> 0 | P11: =IF(OR(A11="B — Process redesign",A11="D — Redesign + targeted staffing"),'Read Me & Assumptions'!$B$36*(12-'Read Me & Assumptions'!$B$35),0)+IF(F11>0,F11*'Read Me & Assumptions'!$B$31*(12-'Read Me & Assumptions'!$B$35),0) -> 2880000 | Q11: =O11-M11 -> -4470000 | R11: =IF(OR(A11="B — Process redesign",A11="D — Redesign + targeted staffing"),'Read Me & Assumptions'!$B$36*12,0)+IF(F11>0,F11*'Read Me & Assumptions'!$B$31*12,0) -> 4320000 | S11: =D11*(1+E11)+F11*G11 -> 204.58333
A12: C — Additional staffing | B12: Base | C12: =AVERAGE('Monthly Demand'!$C$5:$C$16)*(1+'Read Me & Assumptions'!$C$27) -> 213.18 | D12: =AVERAGE('Monthly Demand'!$D$5:$D$16) -> 180.58333 | E12: 0 | F12: ='Read Me & Assumptions'!$C$30 -> 2 | G12: ='Read Me & Assumptions'!$C$37*'Read Me & Assumptions'!$C$34/95 -> 12 | H12: =MIN(C12,D12*(1+E12)+F12*G12) -> 204.58333 | I12: =MAX(0,C12-H12) -> 8.5966667 | J12: 0 | K12: =F12*'Read Me & Assumptions'!$C$33 -> 80000 | L12: =IF(OR(A12="B — Process redesign",A12="D — Redesign + targeted staffing"),'Read Me & Assumptions'!$C$36*12,0)+IF(F12>0,F12*'Read Me & Assumptions'!$C$31*12,0) -> 2400000 | M12: =J12+K12+L12 -> 2480000 | N12: =MAX(0,'Read Me & Assumptions'!$B$8-S12) -> 35.416667 | O12: =IF(OR(A12="B — Process redesign",A12="D — Redesign + targeted staffing"),'Cost Build'!$B$8*'Read Me & Assumptions'!$C$38*'Read Me & Assumptions'!$C$29*(12-'Read Me & Assumptions'!$C$35)/12,0) -> 0 | P12: =IF(OR(A12="B — Process redesign",A12="D — Redesign + targeted staffing"),'Read Me & Assumptions'!$C$36*(12-'Read Me & Assumptions'!$C$35),0)+IF(F12>0,F12*'Read Me & Assumptions'!$C$31*(12-'Read Me & Assumptions'!$C$35),0) -> 1800000 | Q12: =O12-M12 -> -2480000 | R12: =IF(OR(A12="B — Process redesign",A12="D — Redesign + targeted staffing"),'Read Me & Assumptions'!$C$36*12,0)+IF(F12>0,F12*'Read Me & Assumptions'!$C$31*12,0) -> 2400000 | S12: =D12*(1+E12)+F12*G12 -> 204.58333
A13: C — Additional staffing | B13: Optimistic | C13: =AVERAGE('Monthly Demand'!$C$5:$C$16)*(1+'Read Me & Assumptions'!$D$27) -> 211.09 | D13: =AVERAGE('Monthly Demand'!$D$5:$D$16) -> 180.58333 | E13: 0 | F13: ='Read Me & Assumptions'!$D$30 -> 1 | G13: ='Read Me & Assumptions'!$D$37*'Read Me & Assumptions'!$D$34/95 -> 16 | H13: =MIN(C13,D13*(1+E13)+F13*G13) -> 196.58333 | I13: =MAX(0,C13-H13) -> 14.506667 | J13: 0 | K13: =F13*'Read Me & Assumptions'!$D$33 -> 30000 | L13: =IF(OR(A13="B — Process redesign",A13="D — Redesign + targeted staffing"),'Read Me & Assumptions'!$D$36*12,0)+IF(F13>0,F13*'Read Me & Assumptions'!$D$31*12,0) -> 1020000 | M13: =J13+K13+L13 -> 1050000 | N13: =MAX(0,'Read Me & Assumptions'!$B$8-S13) -> 43.416667 | O13: =IF(OR(A13="B — Process redesign",A13="D — Redesign + targeted staffing"),'Cost Build'!$B$8*'Read Me & Assumptions'!$D$38*'Read Me & Assumptions'!$D$29*(12-'Read Me & Assumptions'!$D$35)/12,0) -> 0 | P13: =IF(OR(A13="B — Process redesign",A13="D — Redesign + targeted staffing"),'Read Me & Assumptions'!$D$36*(12-'Read Me & Assumptions'!$D$35),0)+IF(F13>0,F13*'Read Me & Assumptions'!$D$31*(12-'Read Me & Assumptions'!$D$35),0) -> 850000 | Q13: =O13-M13 -> -1050000 | R13: =IF(OR(A13="B — Process redesign",A13="D — Redesign + targeted staffing"),'Read Me & Assumptions'!$D$36*12,0)+IF(F13>0,F13*'Read Me & Assumptions'!$D$31*12,0) -> 1020000 | S13: =D13*(1+E13)+F13*G13 -> 196.58333
A14: D — Redesign + targeted staffing | B14: Conservative | C14: =AVERAGE('Monthly Demand'!$C$5:$C$16)*(1+'Read Me & Assumptions'!$B$27) -> 215.27 | D14: =AVERAGE('Monthly Demand'!$D$5:$D$16) -> 180.58333 | E14: ='Read Me & Assumptions'!$B$28 -> 0.03 | F14: ='Read Me & Assumptions'!$B$30 -> 3 | G14: ='Read Me & Assumptions'!$B$37*'Read Me & Assumptions'!$B$34/95 -> 8 | H14: =MIN(C14,D14*(1+E14)+F14*G14) -> 210.00083 | I14: =MAX(0,C14-H14) -> 5.2691667 | J14: ='Read Me & Assumptions'!$B$32 -> 500000 | K14: =F14*'Read Me & Assumptions'!$B$33 -> 150000 | L14: =IF(OR(A14="B — Process redesign",A14="D — Redesign + targeted staffing"),'Read Me & Assumptions'!$B$36*12,0)+IF(F14>0,F14*'Read Me & Assumptions'!$B$31*12,0) -> 4680000 | M14: =J14+K14+L14 -> 5330000 | N14: =MAX(0,'Read Me & Assumptions'!$B$8-S14) -> 29.999167 | O14: =IF(OR(A14="B — Process redesign",A14="D — Redesign + targeted staffing"),'Cost Build'!$B$8*'Read Me & Assumptions'!$B$38*'Read Me & Assumptions'!$B$29*(12-'Read Me & Assumptions'!$B$35)/12,0) -> 11307.087 | P14: =IF(OR(A14="B — Process redesign",A14="D — Redesign + targeted staffing"),'Read Me & Assumptions'!$B$36*(12-'Read Me & Assumptions'!$B$35),0)+IF(F14>0,F14*'Read Me & Assumptions'!$B$31*(12-'Read Me & Assumptions'!$B$35),0) -> 3120000 | Q14: =O14-M14 -> -5318692.9 | R14: =IF(OR(A14="B — Process redesign",A14="D — Redesign + targeted staffing"),'Read Me & Assumptions'!$B$36*12,0)+IF(F14>0,F14*'Read Me & Assumptions'!$B$31*12,0) -> 4680000 | S14: =D14*(1+E14)+F14*G14 -> 210.00083
A15: D — Redesign + targeted staffing | B15: Base | C15: =AVERAGE('Monthly Demand'!$C$5:$C$16)*(1+'Read Me & Assumptions'!$C$27) -> 213.18 | D15: =AVERAGE('Monthly Demand'!$D$5:$D$16) -> 180.58333 | E15: ='Read Me & Assumptions'!$C$28 -> 0.1 | F15: ='Read Me & Assumptions'!$C$30 -> 2 | G15: ='Read Me & Assumptions'!$C$37*'Read Me & Assumptions'!$C$34/95 -> 12 | H15: =MIN(C15,D15*(1+E15)+F15*G15) -> 213.18 | I15: =MAX(0,C15-H15) -> 0 | J15: ='Read Me & Assumptions'!$C$32 -> 350000 | K15: =F15*'Read Me & Assumptions'!$C$33 -> 80000 | L15: =IF(OR(A15="B — Process redesign",A15="D — Redesign + targeted staffing"),'Read Me & Assumptions'!$C$36*12,0)+IF(F15>0,F15*'Read Me & Assumptions'!$C$31*12,0) -> 2640000 | M15: =J15+K15+L15 -> 3070000 | N15: =MAX(0,'Read Me & Assumptions'!$B$8-S15) -> 17.358333 | O15: =IF(OR(A15="B — Process redesign",A15="D — Redesign + targeted staffing"),'Cost Build'!$B$8*'Read Me & Assumptions'!$C$38*'Read Me & Assumptions'!$C$29*(12-'Read Me & Assumptions'!$C$35)/12,0) -> 38161.417 | P15: =IF(OR(A15="B — Process redesign",A15="D — Redesign + targeted staffing"),'Read Me & Assumptions'!$C$36*(12-'Read Me & Assumptions'!$C$35),0)+IF(F15>0,F15*'Read Me & Assumptions'!$C$31*(12-'Read Me & Assumptions'!$C$35),0) -> 1980000 | Q15: =O15-M15 -> -3031838.6 | R15: =IF(OR(A15="B — Process redesign",A15="D — Redesign + targeted staffing"),'Read Me & Assumptions'!$C$36*12,0)+IF(F15>0,F15*'Read Me & Assumptions'!$C$31*12,0) -> 2640000 | S15: =D15*(1+E15)+F15*G15 -> 222.64167
A16: D — Redesign + targeted staffing | B16: Optimistic | C16: =AVERAGE('Monthly Demand'!$C$5:$C$16)*(1+'Read Me & Assumptions'!$D$27) -> 211.09 | D16: =AVERAGE('Monthly Demand'!$D$5:$D$16) -> 180.58333 | E16: ='Read Me & Assumptions'!$D$28 -> 0.18 | F16: ='Read Me & Assumptions'!$D$30 -> 1 | G16: ='Read Me & Assumptions'!$D$37*'Read Me & Assumptions'!$D$34/95 -> 16 | H16: =MIN(C16,D16*(1+E16)+F16*G16) -> 211.09 | I16: =MAX(0,C16-H16) -> 0 | J16: ='Read Me & Assumptions'!$D$32 -> 250000 | K16: =F16*'Read Me & Assumptions'!$D$33 -> 30000 | L16: =IF(OR(A16="B — Process redesign",A16="D — Redesign + targeted staffing"),'Read Me & Assumptions'!$D$36*12,0)+IF(F16>0,F16*'Read Me & Assumptions'!$D$31*12,0) -> 1200000 | M16: =J16+K16+L16 -> 1480000 | N16: =MAX(0,'Read Me & Assumptions'!$B$8-S16) -> 10.911667 | O16: =IF(OR(A16="B — Process redesign",A16="D — Redesign + targeted staffing"),'Cost Build'!$B$8*'Read Me & Assumptions'!$D$38*'Read Me & Assumptions'!$D$29*(12-'Read Me & Assumptions'!$D$35)/12,0) -> 70669.291 | P16: =IF(OR(A16="B — Process redesign",A16="D — Redesign + targeted staffing"),'Read Me & Assumptions'!$D$36*(12-'Read Me & Assumptions'!$D$35),0)+IF(F16>0,F16*'Read Me & Assumptions'!$D$31*(12-'Read Me & Assumptions'!$D$35),0) -> 1000000 | Q16: =O16-M16 -> -1409330.7 | R16: =IF(OR(A16="B — Process redesign",A16="D — Redesign + targeted staffing"),'Read Me & Assumptions'!$D$36*12,0)+IF(F16>0,F16*'Read Me & Assumptions'!$D$31*12,0) -> 1200000 | S16: =D16*(1+E16)+F16*G16 -> 229.08833
A19: Important
A20: Baseline throughput is average historical completions, not a proven theoretical capacity. Added throughput per FTE and redesign uplifts are provisional assumptions. Modelled throughput is capped at demand. Costs are not netted against benefits because validated cashable savings are not yet established.

Sheet Sensitivity Analysis
A1: Sensitivity Analysis
A2: Editable ranges and linked model outputs; review scenario ranking under assumption changes
A4: Driver | B4: Low | C4: Base | D4: High | E4: Affected outcome | F4: Linked assumption | G4: Interpretation | H4: Status | I4: Low-case uncapped capacity | J4: Base-case uncapped capacity | K4: High-case uncapped capacity | L4: Low-case gap to 240 | M4: Base-case gap to 240 | N4: High-case gap to 240 | O4: Low-case cost / benefit proxy (INR) | P4: Base-case cost / benefit proxy (INR) | Q4: High-case cost / benefit proxy (INR)
A5: Monthly demand growth | B5: 0.01 | C5: 0.02 | D5: 0.03 | E5: Demand and capacity gap | F5: Read Me & Assumptions row 27 | G5: Higher demand may increase backlog even if throughput improves | H5: Modelled; validate assumptions | I5: =AVERAGE('Monthly Demand'!$D$5:$D$16)*(1+'Read Me & Assumptions'!$C$28)+'Read Me & Assumptions'!$C$30*'Read Me & Assumptions'!$C$37 -> 222.64167 | J5: =AVERAGE('Monthly Demand'!$D$5:$D$16)*(1+'Read Me & Assumptions'!$C$28)+'Read Me & Assumptions'!$C$30*'Read Me & Assumptions'!$C$37 -> 222.64167 | K5: =AVERAGE('Monthly Demand'!$D$5:$D$16)*(1+'Read Me & Assumptions'!$C$28)+'Read Me & Assumptions'!$C$30*'Read Me & Assumptions'!$C$37 -> 222.64167 | L5: =MAX(0,'Read Me & Assumptions'!$B$8-I5) -> 17.358333 | M5: =MAX(0,'Read Me & Assumptions'!$B$8-J5) -> 17.358333 | N5: =MAX(0,'Read Me & Assumptions'!$B$8-K5) -> 17.358333
A6: Redesign throughput uplift | B6: 0.03 | C6: 0.1 | D6: 0.18 | E6: Modelled throughput | F6: Read Me & Assumptions row 28 | G6: Assumption needs evidence from a pilot or comparable operation | H6: Modelled; validate assumptions | I6: =AVERAGE('Monthly Demand'!$D$5:$D$16)*(1+B6)+'Read Me & Assumptions'!$C$30*'Read Me & Assumptions'!$C$37 -> 210.00083 | J6: =AVERAGE('Monthly Demand'!$D$5:$D$16)*(1+C6)+'Read Me & Assumptions'!$C$30*'Read Me & Assumptions'!$C$37 -> 222.64167 | K6: =AVERAGE('Monthly Demand'!$D$5:$D$16)*(1+D6)+'Read Me & Assumptions'!$C$30*'Read Me & Assumptions'!$C$37 -> 237.08833 | L6: =MAX(0,'Read Me & Assumptions'!$B$8-I6) -> 29.999167 | M6: =MAX(0,'Read Me & Assumptions'!$B$8-J6) -> 17.358333 | N6: =MAX(0,'Read Me & Assumptions'!$B$8-K6) -> 2.9116667
A7: Rework reduction | B7: 0.05 | C7: 0.15 | D7: 0.25 | E7: Rework cost estimate | F7: Read Me & Assumptions row 29 | G7: Cost sensitivity only; not assumed to create cash savings automatically | H7: Modelled; validate assumptions | I7: =AVERAGE('Monthly Demand'!$D$5:$D$16)*(1+'Read Me & Assumptions'!$C$28)+'Read Me & Assumptions'!$C$30*'Read Me & Assumptions'!$C$37 -> 222.64167 | J7: =AVERAGE('Monthly Demand'!$D$5:$D$16)*(1+'Read Me & Assumptions'!$C$28)+'Read Me & Assumptions'!$C$30*'Read Me & Assumptions'!$C$37 -> 222.64167 | K7: =AVERAGE('Monthly Demand'!$D$5:$D$16)*(1+'Read Me & Assumptions'!$C$28)+'Read Me & Assumptions'!$C$30*'Read Me & Assumptions'!$C$37 -> 222.64167 | L7: =MAX(0,'Read Me & Assumptions'!$B$8-I7) -> 17.358333 | M7: =MAX(0,'Read Me & Assumptions'!$B$8-J7) -> 17.358333 | N7: =MAX(0,'Read Me & Assumptions'!$B$8-K7) -> 17.358333 | O7: ='Cost Build'!$B$10*B7 -> 16960.63 | P7: ='Cost Build'!$B$10*C7 -> 50881.889 | Q7: ='Cost Build'!$B$10*D7 -> 84803.149
A8: Monthly cost per added FTE | B8: 85000 | C8: 100000 | D8: 120000 | E8: Annual recurring staffing cost | F8: Read Me & Assumptions row 31 | G8: Higher cost weakens staffing economics | H8: Modelled; validate assumptions | I8: =AVERAGE('Monthly Demand'!$D$5:$D$16)*(1+'Read Me & Assumptions'!$C$28)+'Read Me & Assumptions'!$C$30*'Read Me & Assumptions'!$C$37 -> 222.64167 | J8: =AVERAGE('Monthly Demand'!$D$5:$D$16)*(1+'Read Me & Assumptions'!$C$28)+'Read Me & Assumptions'!$C$30*'Read Me & Assumptions'!$C$37 -> 222.64167 | K8: =AVERAGE('Monthly Demand'!$D$5:$D$16)*(1+'Read Me & Assumptions'!$C$28)+'Read Me & Assumptions'!$C$30*'Read Me & Assumptions'!$C$37 -> 222.64167 | L8: =MAX(0,'Read Me & Assumptions'!$B$8-I8) -> 17.358333 | M8: =MAX(0,'Read Me & Assumptions'!$B$8-J8) -> 17.358333 | N8: =MAX(0,'Read Me & Assumptions'!$B$8-K8) -> 17.358333 | O8: ='Read Me & Assumptions'!$C$30*B8*12 -> 2040000 | P8: ='Read Me & Assumptions'!$C$30*C8*12 -> 2400000 | Q8: ='Read Me & Assumptions'!$C$30*D8*12 -> 2880000
A9: One-time redesign cost | B9: 250000 | C9: 350000 | D9: 500000 | E9: First-year cost | F9: Read Me & Assumptions row 32 | G9: Estimate requires implementation scope | H9: Modelled; validate assumptions | I9: =AVERAGE('Monthly Demand'!$D$5:$D$16)*(1+'Read Me & Assumptions'!$C$28)+'Read Me & Assumptions'!$C$30*'Read Me & Assumptions'!$C$37 -> 222.64167 | J9: =AVERAGE('Monthly Demand'!$D$5:$D$16)*(1+'Read Me & Assumptions'!$C$28)+'Read Me & Assumptions'!$C$30*'Read Me & Assumptions'!$C$37 -> 222.64167 | K9: =AVERAGE('Monthly Demand'!$D$5:$D$16)*(1+'Read Me & Assumptions'!$C$28)+'Read Me & Assumptions'!$C$30*'Read Me & Assumptions'!$C$37 -> 222.64167 | L9: =MAX(0,'Read Me & Assumptions'!$B$8-I9) -> 17.358333 | M9: =MAX(0,'Read Me & Assumptions'!$B$8-J9) -> 17.358333 | N9: =MAX(0,'Read Me & Assumptions'!$B$8-K9) -> 17.358333 | O9: =B9+'Read Me & Assumptions'!$C$36*12 -> 490000 | P9: =C9+'Read Me & Assumptions'!$C$36*12 -> 590000 | Q9: =D9+'Read Me & Assumptions'!$C$36*12 -> 740000
A10: Added throughput per FTE | B10: 8 | C10: 12 | D10: 16 | E10: Modelled throughput | F10: Read Me & Assumptions row 37 | G10: Must be validated against operational capacity evidence | H10: Modelled; validate assumptions | I10: =AVERAGE('Monthly Demand'!$D$5:$D$16)*(1+'Read Me & Assumptions'!$C$28)+'Read Me & Assumptions'!$C$30*B10 -> 214.64167 | J10: =AVERAGE('Monthly Demand'!$D$5:$D$16)*(1+'Read Me & Assumptions'!$C$28)+'Read Me & Assumptions'!$C$30*C10 -> 222.64167 | K10: =AVERAGE('Monthly Demand'!$D$5:$D$16)*(1+'Read Me & Assumptions'!$C$28)+'Read Me & Assumptions'!$C$30*D10 -> 230.64167 | L10: =MAX(0,'Read Me & Assumptions'!$B$8-I10) -> 25.358333 | M10: =MAX(0,'Read Me & Assumptions'!$B$8-J10) -> 17.358333 | N10: =MAX(0,'Read Me & Assumptions'!$B$8-K10) -> 9.3583333
A13: Sensitivity interpretation
A14: Throughput columns show uncapped modelled capacity so the 240 target gap remains visible. Demand-capped throughput is retained in Intervention Scenarios column H; demand gap remains column I. Low/base/high values are stress tests, not confidence intervals. Rework cost reductions are effort-cost proxies, not proven cash savings.

Sheet Recommendation
A1: Recommendation & Decision Gate
A2: Decision support only: preferred option must follow validated model outputs and justified assumptions
A4: Management question | B4: Which intervention most defensibly closes the monthly demand gap without unacceptable cost or risk?
A6: Option | B6: Base-case demand | C6: Base-case throughput | D6: Gap to demand | E6: First-year modelled cost | F6: Key trade-off | G6: Assessment | H6: Gap to 240 target | I6: Recurring annual cost | J6: Net first-year impact (proxy only)
A7: A — No change | B7: ='Intervention Scenarios'!C6 -> 213.18 | C7: ='Intervention Scenarios'!H6 -> 180.58333 | D7: ='Intervention Scenarios'!I6 -> 32.596667 | E7: ='Intervention Scenarios'!M6 -> 0 | F7: No implementation cost; backlog risk may persist | G7: =IF(H7=0,"240 target met in base assumptions","240 target gap remains") -> 240 target gap remains | H7: ='Intervention Scenarios'!N6 -> 59.416667 | I7: ='Intervention Scenarios'!R6 -> 0 | J7: ='Intervention Scenarios'!Q6 -> 0
A8: B — Process redesign | B8: ='Intervention Scenarios'!C9 -> 213.18 | C8: ='Intervention Scenarios'!H9 -> 198.64167 | D8: ='Intervention Scenarios'!I9 -> 14.538333 | E8: ='Intervention Scenarios'!M9 -> 590000 | F8: May improve throughput and reduce rework; uplift unverified | G8: =IF(H8=0,"240 target met in base assumptions","240 target gap remains") -> 240 target gap remains | H8: ='Intervention Scenarios'!N9 -> 41.358333 | I8: ='Intervention Scenarios'!R9 -> 240000 | J8: ='Intervention Scenarios'!Q9 -> -551838.58
A9: C — Additional staffing | B9: ='Intervention Scenarios'!C12 -> 213.18 | C9: ='Intervention Scenarios'!H12 -> 204.58333 | D9: ='Intervention Scenarios'!I12 -> 8.5966667 | E9: ='Intervention Scenarios'!M12 -> 2480000 | F9: Adds recurring cost; actual staffing need unverified | G9: =IF(H9=0,"240 target met in base assumptions","240 target gap remains") -> 240 target gap remains | H9: ='Intervention Scenarios'!N12 -> 35.416667 | I9: ='Intervention Scenarios'!R12 -> 2400000 | J9: ='Intervention Scenarios'!Q12 -> -2480000
A10: D — Redesign + targeted staffing | B10: ='Intervention Scenarios'!C15 -> 213.18 | C10: ='Intervention Scenarios'!H15 -> 213.18 | D10: ='Intervention Scenarios'!I15 -> 0 | E10: ='Intervention Scenarios'!M15 -> 3070000 | F10: Potential combined benefit; interaction and costs require validation | G10: =IF(H10=0,"240 target met in base assumptions","240 target gap remains") -> 240 target gap remains | H10: ='Intervention Scenarios'!N15 -> 17.358333 | I10: ='Intervention Scenarios'!R15 -> 2640000 | J10: ='Intervention Scenarios'!Q15 -> -3031838.6
A13: Recommendation status
A14: CONDITIONAL — No option should be declared a winner from synthetic assumptions alone. Compare the base-case gap to 240, first-year and recurring costs, and the rework-cost reduction proxy. If no option closes the target gap, pilot the lowest-risk feasible option and validate throughput, staffing and cashable benefits before approval.
A18: Decision criteria
A19: 1. Meet demand sustainably, not just in a single month.
A20: 2. Compare first-year costs separately from recurring annual costs.
A21: 3. Do not treat released staff time as cash savings without evidence of cash expenditure reduction.
A22: 4. Check the effect of demand growth, intervention effectiveness, staffing cost and implementation cost.
A23: 5. If no option closes the gap, report the residual gap and the next evidence or intervention required.
